aws_sso/__init__.py
aws_sso/abstract.py
aws_sso/command_line.py
aws_sso/model.py
aws_sso/data/hello.txt
aws_sso/services/__init__.py
aws_sso/services/default/__init__.py
aws_sso/services/default/core.py
aws_sso/services/default/params.py
aws_sso/services/default/worker.py
aws_sso/services/discovery/__init__.py
aws_sso/services/discovery/core.py
aws_sso/services/discovery/model.py
aws_sso/services/discovery/params.py
aws_sso/services/discovery/worker.py
aws_sso/services/hello/__init__.py
aws_sso/services/hello/params.py
aws_sso/services/hello/worker.py
aws_sso/services/login/__init__.py
aws_sso/services/login/core.py
aws_sso/services/login/model.py
aws_sso/services/login/params.py
aws_sso/services/login/worker.py
aws_sso/services/sites/__init__.py
aws_sso/services/sites/model.py
aws_sso/services/sites/params.py
aws_sso/services/sites/worker.py
aws_sso/utils/__init__.py
aws_sso/utils/command_line.py
aws_sso/utils/config.py
aws_sso/utils/mockio.py
aws_sso/utils/named_tuple.py
aws_sso/utils/package.py
aws_sso/utils/registry.py
aws_sso/utils/string.py
aws_sso-0.0.2.dist-info/LICENSE
aws_sso-0.0.2.dist-info/METADATA
aws_sso-0.0.2.dist-info/WHEEL
aws_sso-0.0.2.dist-info/entry_points.txt
aws_sso-0.0.2.dist-info/top_level.txt
aws_sso-0.0.2.dist-info/RECORD
