Metadata-Version: 2.1
Name: aws-sso
Version: 0.0.2
Summary: UNKNOWN
Home-page: https://github.com/rkhullar/aws-sso
Author: Rajan Khullar
Author-email: rkhullar03@gmail.com
License: MIT
Keywords: aws sso
Platform: UNKNOWN
Requires-Python: ~=3.6
Requires-Dist: beautifulsoup4 (~=4.8)
Requires-Dist: boto3 (~=1.10)
Requires-Dist: html5lib (~=1.0)
Requires-Dist: keyring (~=19.2)
Requires-Dist: requests (~=2.22)
Requires-Dist: requests-ntlm (~=1.1)
